bak2zip/__init__.py
Bak2ZIP-0.0.1.dist-info/LICENSE
Bak2ZIP-0.0.1.dist-info/METADATA
Bak2ZIP-0.0.1.dist-info/WHEEL
Bak2ZIP-0.0.1.dist-info/top_level.txt
Bak2ZIP-0.0.1.dist-info/RECORD
