Metadata-Version: 2.1
Name: Bak2ZIP
Version: 0.0.1
Summary: Bak2ZIP ——一键备份你的所有重要文件，让你不再为丢失文件而烦恼！
Home-page: https://github.com/CHUA-X/Bak2ZIP
Author: CHUA某人
Author-email: CHUA某人 <chua-x@outlook.com>
Project-URL: Homepage, https://github.com/CHUA-X/Bak2ZIP
Project-URL: Bug Tracker, https://github.com/CHUA-X/Bak2ZIP/issues
Classifier: Development Status :: 3 - Alpha
Classifier: Programming Language :: Python
Classifier: Programming Language :: Python :: 3
Classifier: Programming Language :: Python :: 3 :: Only
Classifier: License :: OSI Approved :: MIT License
Classifier: Natural Language :: Chinese (Simplified)
Classifier: Natural Language :: English
Classifier: Operating System :: Unix
Classifier: Operating System :: POSIX :: Linux
Classifier: Operating System :: MacOS :: MacOS X
Classifier: Operating System :: Microsoft :: Windows
Requires-Python: >=3.6
License-File: LICENSE
